{
    "domain": {
        "display_name": "domain",
        "description": "Please enter your domain",
        "type": "text",
        "required": true
    },
    "apikey": {
        "display_name": "apikey",
        "description": "Please enter your apikey",
        "type": "text",
        "required": true
    },
    "group_approval_id": {
        "display_name": "group_approval_id",
        "description": "Please enter your group_approval_id",
        "type": "text",
        "required": true
    },
    "email_template_id": {
        "display_name": "email_template_id",
        "description": "Please enter your email_template_id",
        "type": "text",
        "required": true
    },
    "sr_category_id": {
        "display_name": "sr_category_id",
        "description": "Please enter your sr_category_id",
        "type": "text",
        "required": true
    },
    "state_approval_id": {
        "display_name": "state_approval_id",
        "description": "Please enter your state_approval_id",
        "type": "text",
        "required": true
    },
    "workspace_id": {
        "display_name": "workspace_id",
        "description": "Please enter your workspace_id",
        "type": "text",
        "required": true
    },
    "document_template_id": {
        "display_name": "document_template_id",
        "description": "Please enter your document_template_id",
        "type": "text",
        "required": true
    },
    "tabs_id": {
        "display_name": "tabs_id",
        "description": "Please enter your tabs_id",
        "type": "text",
        "required": true
    },
    "process_approval_state_id": {
        "display_name": "process_approval_state_id",
        "description": "Please enter your process_approval_state_id",
        "type": "text",
        "required": true
    },
    "process_condition_state_id": {
        "display_name": "process_condition_state_id",
        "description": "Please enter your process_condition_state_id",
        "type": "text",
        "required": true
    },
    "process_file_generation_id": {
        "display_name": "process_file_generation_id",
        "description": "Please enter your process_file_generation_id",
        "type": "text",
        "required": true
    },
    "tab_permission_id": {
        "display_name": "tab_permission_id",
        "description": "Please enter your tab_permission_id",
        "type": "text",
        "required": true
    }
}